Workbook

Sheet Assumptions
A1: Assumptions
A3: Benefits load (% of salary) | B3: 0.22
A4: Travel per head (annual) | B4: 6500
A5: Software per head (annual) | B5: 2400
A6: Merit increase | B6: 0.04

Sheet Teams
A1: Code | B1: Team | C1: Headcount | D1: Avg Salary
A2: ENG | B2: Engineering | C2: 14 | D2: 145000
A3: SAL | B3: Sales | C3: 9 | D3: 98000
A4: MKT | B4: Marketing | C4: 5 | D4: 91000
A5: OPS | B5: Operations | C5: 6 | D5: 76000
A6: FIN | B6: Finance | C6: 3 | D6: 104000

Sheet Calc
A1: Code | B1: Team | C1: Headcount | D1: Salary cost | E1: Benefits | F1: Travel | G1: Software | H1: Total cost
A2: =Teams!A2 -> ENG | B2: =INDEX(Teams!$B$2:$B$6,MATCH(A2,Teams!$A$2:$A$6,0)) -> Engineering | C2: =Teams!C2 -> 14 | D2: =C2*Teams!D2*(1+Assumptions!$B$6) -> 2111200 | E2: =D2*Assumptions!$B$3 -> 464464 | F2: =C2*Assumptions!$B$4 -> 91000 | G2: =C2*Assumptions!$B$5 -> 33600 | H2: =ROUND(SUM(D2:G2),2) -> 2700264
A3: =Teams!A3 -> SAL | B3: =INDEX(Teams!$B$2:$B$6,MATCH(A3,Teams!$A$2:$A$6,0)) -> Sales | C3: =Teams!C3 -> 9 | D3: =C3*Teams!D3*(1+Assumptions!$B$6) -> 917280 | E3: =D3*Assumptions!$B$3 -> 201801.6 | F3: =C3*Assumptions!$B$4 -> 58500 | G3: =C3*Assumptions!$B$5 -> 21600 | H3: =ROUND(SUM(D3:G3),2) -> 1199181.6
A4: =Teams!A4 -> MKT | B4: =INDEX(Teams!$B$2:$B$6,MATCH(A4,Teams!$A$2:$A$6,0)) -> Marketing | C4: =Teams!C4 -> 5 | D4: =C4*Teams!D4*(1+Assumptions!$B$6) -> 473200 | E4: =D4*Assumptions!$B$3 -> 104104 | F4: =C4*Assumptions!$B$4 -> 32500 | G4: =C4*Assumptions!$B$5 -> 12000 | H4: =ROUND(SUM(D4:G4),2) -> 621804
A5: =Teams!A5 -> OPS | B5: =INDEX(Teams!$B$2:$B$6,MATCH(A5,Teams!$A$2:$A$6,0)) -> Operations | C5: =Teams!C5 -> 6 | D5: =C5*Teams!D5*(1+Assumptions!$B$6) -> 474240 | E5: =D5*Assumptions!$B$3 -> 104332.8 | F5: =C5*Assumptions!$B$4 -> 39000 | G5: =C5*Assumptions!$B$5 -> 14400 | H5: =ROUND(SUM(D5:G5),2) -> 631972.8
A6: =Teams!A6 -> FIN | B6: =INDEX(Teams!$B$2:$B$6,MATCH(A6,Teams!$A$2:$A$6,0)) -> Finance | C6: =Teams!C6 -> 3 | D6: =C6*Teams!D6*(1+Assumptions!$B$6) -> 324480 | E6: =D6*Assumptions!$B$3 -> 71385.6 | F6: =C6*Assumptions!$B$4 -> 19500 | G6: =C6*Assumptions!$B$5 -> 7200 | H6: =ROUND(SUM(D6:G6),2) -> 422565.6

Sheet Summary
A1: FY27 Team Budget - Summary
A3: Team | B3: Total cost | C3: Share of total
A4: =Calc!B2 -> Engineering | B4: =Calc!H2 -> 2700264 | C4: =B4/$B$10 -> 0.48428384
A5: =Calc!B3 -> Sales | B5: =Calc!H3 -> 1199181.6 | C5: =B5/$B$10 -> 0.21506944
A6: =Calc!B4 -> Marketing | B6: =Calc!H4 -> 621804 | C6: =B6/$B$10 -> 0.11151859
A7: =Calc!B5 -> Operations | B7: =Calc!H5 -> 631972.8 | C7: =B7/$B$10 -> 0.11334233
A8: =Calc!B6 -> Finance | B8: =Calc!H6 -> 422565.6 | C8: =B8/$B$10 -> 0.075785808
A10: Total | B10: =SUM(B4:B8) -> 5575788
A11: Total headcount | B11: =SUM(Calc!C2:C6) -> 37
A12: Cost per head | B12: =ROUND(B10/B11,2) -> 150696.97
