Workbook
Name Growth_Rate: Assumptions!$C$5
Name GrowthRate: Assumptions!#REF!
Name OpeningCash: Assumptions!$C$8

Sheet Summary
A1: FY27 Rolling Forecast - Summary
A2: MASTER - do not edit. Links to Budget file. Last reviewed by FP&A.
A4: Metric | B4: FY27
A5: FY revenue (forecast) | B5: =Forecast!C17 -> 30277165
A6: FY EBITDA | B6: =Forecast!G17 -> 5643585.2
A7: EBITDA margin | B7: =B6/B5 -> 0.18639741
A8: Closing cash (Dec-27) | B8: =Cash!F15 -> 7850462.8
A9: Revenue volatility (avg MoM % change) | B9: =AVERAGE(Forecast!I6:I16) -> 0.20954893
A10: Spotlight product revenue (selected month) | B10: =Forecast!E2 -> 75400

Sheet Forecast
A1: FY27 Rolling Forecast
A2: Spotlight month | B2: Mar | D2: Spotlight: Nimbus Edge revenue | E2: =INDIRECT("'"&$B$2&"'!C12") -> 75400
A4: Month | B4: Plan Revenue | C4: Forecast Revenue | D4: COGS | E4: Gross Margin | F4: Opex | G4: EBITDA | H4: One-offs | I4: MoM change (vs avg of two months)
A5: 46388 | B5: =Jan!C50 -> 2452400 | C5: =B5*(1+Growth_Rate) -> 2525972 | D5: =Jan!D50 -> 1164300 | E5: =C5-D5 -> 1361672 | F5: =Assumptions!$C$30 -> 888000 | G5: =E5-F5+H5 -> 473672 | H5: =SUMPRODUCT((MONTH(DATEVALUE(Assumptions!$B$34:$B$37))=MONTH($A5))*Assumptions!$C$34:$C$37) -> 0
A6: 46419 | B6: =Feb!C50 -> 2448300 | C6: =B6*(1+Growth_Rate) -> 2521749 | D6: =Feb!D50 -> 1158000 | E6: =C6-D6 -> 1363749 | F6: =Assumptions!$C$30 -> 888000 | G6: =E6-F6+H6 -> 475749 | H6: =SUMPRODUCT((MONTH(DATEVALUE(Assumptions!$B$34:$B$37))=MONTH($A6))*Assumptions!$C$34:$C$37) -> 0 | I6: =ABS(C6-C5)/(C5+C6) -> 0.00083661518
A7: 46447 | B7: =Mar!C50 -> 2813000 | C7: =B7*(1+Growth_Rate) -> 2897390 | D7: =Mar!D50 -> 1333700 | E7: =C7-D7 -> 1563690 | F7: =Assumptions!$C$30 -> 888000 | G7: =E7-F7+H7 -> 675690 | H7: =SUMPRODUCT((MONTH(DATEVALUE(Assumptions!$B$34:$B$37))=MONTH($A7))*Assumptions!$C$34:$C$37) -> 0 | I7: =ABS(C7-C6)/(C6+C7) -> 0.069317469
A8: 46478 | B8: =Apr!C50 -> 2588500 | C8: =IFERROR(B8*(1+GrowthRate),B8) -> 2588500 | D8: =Apr!D50 -> 1227300 | E8: =C8-D8 -> 1361200 | F8: =Assumptions!$C$30 -> 888000 | G8: =E8-F8+H8 -> 558200 | H8: =SUMPRODUCT((MONTH(DATEVALUE(Assumptions!$B$34:$B$37))=MONTH($A8))*Assumptions!$C$34:$C$37) -> 85000 | I8: =ABS(C8-C7)/(C7+C8) -> 0.056306269
A9: 46508 | B9: =May!C50 -> 2611700 | C9: =IFERROR(B9*(1+GrowthRate),B9) -> 2611700 | D9: =May!D50 -> 1236700 | E9: =C9-D9 -> 1375000 | F9: =Assumptions!$C$30 -> 888000 | G9: =E9-F9+H9 -> 487000 | H9: =SUMPRODUCT((MONTH(DATEVALUE(Assumptions!$B$34:$B$37))=MONTH($A9))*Assumptions!$C$34:$C$37) -> 0 | I9: =ABS(C9-C8)/(C8+C9) -> 0.0044613669
A10: 46539 | B10: =Jun!C50 -> 2762200 | C10: =B10*(1+Growth_Rate) -> 2845066 | D10: =Jun!D50 -> 1316600 | E10: =C10-D10 -> 1528466 | F10: =Assumptions!$C$30 -> 888000 | G10: =E10-F10+H10 -> 680466 | H10: =SUMPRODUCT((MONTH(DATEVALUE(Assumptions!$B$34:$B$37))=MONTH($A10))*Assumptions!$C$34:$C$37) -> 40000 | I10: =ABS(C10-C9)/(C9+C10) -> 0.042766356
A11: 46569 | B11: =Jul!C50 -> 2516100 | C11: =B11*(1+Growth_Rate) -> 2591583 | D11: =Jul!D50 -> 1189600 | E11: =C11-D11 -> 1401983 | F11: =Assumptions!$C$30 -> 888000 | G11: =E11-F11+H11 -> 513983 | H11: =SUMPRODUCT((MONTH(DATEVALUE(Assumptions!$B$34:$B$37))=MONTH($A11))*Assumptions!$C$34:$C$37) -> 0 | I11: =ABS(C11-C10)/(C10+C11) -> 0.04662486
A12: 46600 | B12: =Aug!C50 -> 2483.8 | C12: =B12*(1+Growth_Rate) -> 2558.314 | D12: =Aug!D50 -> 1180.1 | E12: =C12-D12 -> 1378.214 | F12: =Assumptions!$C$30 -> 888000 | G12: =E12-F12+H12 -> -886621.79 | H12: =SUMPRODUCT((MONTH(DATEVALUE(Assumptions!$B$34:$B$37))=MONTH($A12))*Assumptions!$C$34:$C$37) -> 0 | I12: =ABS(C12-C11)/(C11+C12) -> 0.99802762
A13: 46631 | B13: =Sep!C50 -> 2847300 | C13: =IFERROR(B13*(1+GrowthRate),B13) -> 2847300 | D13: =Sep!D50 -> 1344900 | E13: =C13-D13 -> 1502400 | F13: =Assumptions!$C$30 -> 888000 | G13: =E13-F13+H13 -> 554400 | H13: =SUMPRODUCT((MONTH(DATEVALUE(Assumptions!$B$34:$B$37))=MONTH($A13))*Assumptions!$C$34:$C$37) -> -60000 | I13: =ABS(C13-C12)/(C12+C13) -> 0.9982046
A14: 46661 | B14: =Oct!C50 -> 2690000 | C14: =B14*(1+Growth_Rate) -> 2770700 | D14: =Oct!D50 -> 1283000 | E14: =C14-D14 -> 1487700 | F14: =Assumptions!$C$30 -> 888000 | G14: =E14-F14+H14 -> 624700 | H14: =SUMPRODUCT((MONTH(DATEVALUE(Assumptions!$B$34:$B$37))=MONTH($A14))*Assumptions!$C$34:$C$37) -> 25000 | I14: =ABS(C14-C13)/(C13+C14) -> 0.013634745
A15: 46692 | B15: =Nov!C50 -> 2772500 | C15: 2856000 | D15: =Nov!D50 -> 1322800 | E15: =C15-D15 -> 1533200 | F15: =Assumptions!$C$30 -> 888000 | G15: =E15-F15+H15 -> 645200 | H15: =SUMPRODUCT((MONTH(DATEVALUE(Assumptions!$B$34:$B$37))=MONTH($A15))*Assumptions!$C$34:$C$37) -> 0 | I15: =ABS(C15-C14)/(C14+C15) -> 0.015159863
A16: 46722 | B16: =Dec!C50 -> 3124900 | C16: =B16*(1+Growth_Rate) -> 3218647 | D16: =Dec!D50 -> 1489500 | E16: =C16-D16 -> 1729147 | F16: =Assumptions!$C$30 -> 888000 | G16: =E16-F16+H16 -> 841147 | H16: =SUMPRODUCT((MONTH(DATEVALUE(Assumptions!$B$34:$B$37))=MONTH($A16))*Assumptions!$C$34:$C$37) -> 0 | I16: =ABS(C16-C15)/(C15+C16) -> 0.059698448
A17: FY27 | B17: =SUM(B5:B16) -> 29629384 | C17: =SUM(C5:C16) -> 30277165 | D17: =SUM(D5:D16) -> 14067580 | E17: =SUM(E5:E16) -> 16209585 | F17: =SUM(F5:F16) -> 10656000 | G17: =SUM(G5:G16) -> 5643585.2 | H17: =SUM(H5:H16) -> 90000

Sheet Cash
A1: Cash bridge FY27
A2: Interest earned on average monthly balance. Iterative calculation must be ON.
A3: Month | B3: Opening Cash | C3: EBITDA | D3: Capex | E3: Interest | F3: Closing Cash
A4: =Forecast!A5 -> 46388 | B4: =Assumptions!C8 -> 2500000 | C4: =Forecast!G5 -> 473672 | D4: =Assumptions!$C$9/12 -> 50000 | E4: =(B4+F4)/2*Assumptions!$C$10/12 -> 13593.163 | F4: =B4+C4-D4+E4 -> 2937265.2
A5: =Forecast!A6 -> 46419 | B5: =F4 -> 2937265.2 | C5: =Forecast!G6 -> 475749 | D5: =Assumptions!$C$9/12 -> 50000 | E5: =(B5+F5)/2*Assumptions!$C$10/12 -> 15790.174 | F5: =B5+C5-D5+E5 -> 3378804.3
A6: =Forecast!A7 -> 46447 | B6: =F5 -> 3378804.3 | C6: =Forecast!G7 -> 675690 | D6: =Assumptions!$C$9/12 -> 50000 | E6: =(B6+F6)/2*Assumptions!$C$10/12 -> 18504.508 | F6: =B6+C6-D6+E6 -> 4022998.8
A7: =Forecast!A8 -> 46478 | B7: =F6 -> 4022998.8 | C7: =Forecast!G8 -> 558200 | D7: =Assumptions!$C$9/12 -> 50000 | E7: =(B7+F7)/2*Assumptions!$C$10/12 -> 21439.092 | F7: =B7+C7-D7+E7 -> 4552637.9
A8: =Forecast!A9 -> 46508 | B8: =F7 -> 4552637.9 | C8: =Forecast!G9 -> 487000 | D8: =Assumptions!$C$9/12 -> 50000 | E8: =(B8+F8)/2*Assumptions!$C$10/12 -> 23915.478 | F8: =B8+C8-D8+E8 -> 5013553.4
A9: =Forecast!A10 -> 46539 | B9: =F8 -> 5013553.4 | C9: =Forecast!G10 -> 680466 | D9: =Assumptions!$C$9/12 -> 50000 | E9: =(B9+F9)/2*Assumptions!$C$10/12 -> 26710.709 | F9: =B9+C9-D9+E9 -> 5670730.1
A10: =Forecast!A11 -> 46569 | B10: =F9 -> 5670730.1 | C10: =Forecast!G11 -> 513983 | D10: =Assumptions!$C$9/12 -> 50000 | E10: =(B10+F10)/2*Assumptions!$C$10/12 -> 29587.577 | F10: =B10+C10-D10+E10 -> 6164300.7
A11: =Forecast!A12 -> 46600 | B11: =F10 -> 6164300.7 | C11: =Forecast!G12 -> -886621.79 | D11: =Assumptions!$C$9/12 -> 50000 | E11: =(B11+F11)/2*Assumptions!$C$10/12 -> 28551.327 | F11: =B11+C11-D11+E11 -> 5256230.2
A12: =Forecast!A13 -> 46631 | B12: =F11 -> 5256230.2 | C12: =Forecast!G13 -> 554400 | D12: =Assumptions!$C$9/12 -> 50000 | E12: =(B12+F12)/2*Assumptions!$C$10/12 -> 27611.179 | F12: =B12+C12-D12+E12 -> 5788241.4
A13: =Forecast!A14 -> 46661 | B13: =F12 -> 5788241.4 | C13: =Forecast!G14 -> 624700 | D13: =Assumptions!$C$9/12 -> 50000 | E13: =(B13+F13)/2*Assumptions!$C$10/12 -> 30454.092 | F13: =B13+C13-D13+E13 -> 6393395.5
A14: =Forecast!A15 -> 46692 | B14: =F13 -> 6393395.5 | C14: =Forecast!G15 -> 645200 | D14: =Assumptions!$C$9/12 -> 50000 | E14: =(B14+F14)/2*Assumptions!$C$10/12 -> 33538.825 | F14: =B14+C14-D14+E14 -> 7022134.3
A15: =Forecast!A16 -> 46722 | B15: =F14 -> 7022134.3 | C15: =Forecast!G16 -> 841147 | D15: =Assumptions!$C$9/12 -> 50000 | E15: =(B15+F15)/2*Assumptions!$C$10/12 -> 37181.493 | F15: =B15+C15-D15+E15 -> 7850462.8

Sheet Assumptions
A1: Assumptions - FY27
A2: Yellow cells are inputs. Owner: FP&A.
A3: Driver | C3: Value | D3: Notes
A5: Forecast uplift vs plan (monthly) | C5: 0.03 | D5: Board-approved uplift
A6: FX USD/INR (planning rate) | C6: 83.5
A8: Opening cash (1-Jan-27) | C8: 2500000 | D8: Per Dec-26 bank recon
A9: Annual capex | C9: 600000 | D9: Spread evenly
A10: Interest on cash balance (annual) | C10: 0.06 | D10: On average monthly balance
A12: Monthly opex inputs (USD) | C12: Value
A13: Salaries | C13: 420000
A14: Marketing - events | C14: 18000
A15: Marketing - digital | C15: 22000
A16: Marketing - agencies | C16: 9500
A17: Rent | C17: 55000
A18: IT & cloud | C18: 38000
A19: Regional opex budget FY27 (annual) | C19: Value | D19: Source
A20: North America | C20: =[1]Regional!C5 -> 1800000 | D20: Budget file (Finance)
A21: EMEA | C21: =[1]Regional!C6 -> 1200000 | D21: Budget file (Finance)
A22: APAC | C22: =[1]Regional!C7 -> 900000 | D22: Budget file (Finance)
A23: India | C23: =[1]Regional!C8 -> 600000 | D23: Budget file (Finance)
A24: Opex subtotals (monthly) | C24: Value
A25: Salaries | C25: =C13 -> 420000
A26: Rent & IT | C26: =C17+C18 -> 93000
A27: Marketing | C27: =IFERROR(SUM(C14:C16)+#REF!,0) -> 0
A28: Regional opex | C28: =SUM(C20:C23)/12 -> 375000
A30: Total monthly opex | C30: =SUM(C25:C28) -> 888000
A33: One-off items | B33: Date | C33: Amount (USD)
A34: Q1 trade-show rebate (Mar) | B34: 03/04/2027 | C34: 85000
A35: Insurance recovery | B35: 2027-06-15 | C35: 40000
A36: Lease exit fee - Bengaluru (Sep) | B36: 11/09/2027 | C36: -60000
A37: Grant income | B37: 2027-10-01 | C37: 25000

Sheet Jan
A1: Jan 2027 - product revenue plan
A2: Units: USD
A4: Product line | B4: Category | C4: Revenue | D4: COGS
A5: Atlas Core | B5: Subscriptions | C5: 98200 | D5: 39100
A6: Atlas Pro | B6: Subscriptions | C6: 36100 | D6: 17100
A7: Atlas Edge | B7: Hardware | C7: 98500 | D7: 49700
A8: Atlas Implementation | B8: Services | C8: 76900 | D8: 36800
A9: Atlas Academy | B9: Training | C9: 32000 | D9: 10800
A10: Nimbus Core | B10: Subscriptions | C10: 100300 | D10: 41000
A11: Nimbus Pro | B11: Subscriptions | C11: 66400 | D11: 32700
A12: Nimbus Edge | B12: Hardware | C12: 64500 | D12: 32000
A13: Nimbus Implementation | B13: Services | C13: 76900 | D13: 24400
A14: Nimbus Academy | B14: Training | C14: 87600 | D14: 22700
A15: Vega Core | B15: Subscriptions | C15: 29300 | D15: 11700
A16: Vega Pro | B16: Subscriptions | C16: 36200 | D16: 9400
... A49: Zephyr Academy (launch FY27) | B49: Training | C49: 101600 | D49: 50100
A50: Total | C50: =SUM(C5:C44) -> 2452400 | D50: =SUM(D5:D49) -> 1164300

Sheet Feb
A1: Feb 2027 - product revenue plan
A2: Units: USD
A4: Product line | B4: Category | C4: Revenue | D4: COGS
A5: Atlas Core | B5: Subscriptions | C5: 105500 | D5: 42000
A6: Atlas Pro | B6: Subscriptions | C6: 36200 | D6: 17100
A7: Atlas Edge | B7: Hardware | C7: 99800 | D7: 50400
A8: Atlas Implementation | B8: Services | C8: 76400 | D8: 36500
A9: Atlas Academy | B9: Training | C9: 29600 | D9: 10000
A10: Nimbus Core | B10: Subscriptions | C10: 105600 | D10: 43200
A11: Nimbus Pro | B11: Subscriptions | C11: 66200 | D11: 32600
A12: Nimbus Edge | B12: Hardware | C12: 57900 | D12: 28700
A13: Nimbus Implementation | B13: Services | C13: 72600 | D13: 23100
A14: Nimbus Academy | B14: Training | C14: 95200 | D14: 24700
A15: Vega Core | B15: Subscriptions | C15: 26900 | D15: 10700
A16: Vega Pro | B16: Subscriptions | C16: 37600 | D16: 9800
... A49: Zephyr Academy (launch FY27) | B49: Training | C49: 93700 | D49: 46200
A50: Total | C50: =SUM(C5:C44) -> 2448300 | D50: =SUM(D5:D49) -> 1158000

Sheet Mar
A1: Mar 2027 - product revenue plan
A2: Units: USD
A4: Product line | B4: Category | C4: Revenue | D4: COGS
A5: Atlas Core | B5: Subscriptions | C5: 112700 | D5: 44900
A6: Atlas Pro | B6: Subscriptions | C6: 40100 | D6: 19000
A7: Atlas Edge | B7: Hardware | C7: 118800 | D7: 60000
A8: Atlas Implementation | B8: Services | C8: 93600 | D8: 44800
A9: Atlas Academy | B9: Training | C9: 35600 | D9: 12000
A10: Nimbus Core | B10: Subscriptions | C10: 119300 | D10: 48800
A11: Nimbus Pro | B11: Subscriptions | C11: 77500 | D11: 38200
A12: Nimbus Edge | B12: Hardware | C12: 75400 | D12: 37400
A13: Nimbus Implementation | B13: Services | C13: 89700 | D13: 28500
A14: Nimbus Academy | B14: Training | C14: 106200 | D14: 27500
A15: Vega Core | B15: Subscriptions | C15: 33400 | D15: 13300
A16: Vega Pro | B16: Subscriptions | C16: 46000 | D16: 12000
... A49: Zephyr Academy (launch FY27) | B49: Training | C49: 105300 | D49: 51900
A50: Total | C50: =SUM(C5:C44) -> 2813000 | D50: =SUM(D5:D49) -> 1333700

Sheet Apr
A1: Apr 2027 - product revenue plan
A2: Units: USD
A4: Product line | B4: Category | C4: Revenue | D4: COGS
A5: Atlas Core | B5: Subscriptions | C5: 110100 | D5: 43800
A6: Atlas Pro | B6: Subscriptions | C6: 38400 | D6: 18200
A7: Atlas Edge | B7: Hardware | C7: 111000 | D7: 56000
A8: Atlas Implementation | B8: Services | C8: 82900 | D8: 39600
A9: Atlas Academy | B9: Training | C9: 35500 | D9: 11900
A10: Nimbus Core | B10: Subscriptions | C10: 107900 | D10: 44200
A11: Nimbus Pro | B11: Subscriptions | C11: 64400 | D11: 31700
A12: Nimbus Edge | B12: Hardware | C12: 62300 | D12: 30900
A13: Nimbus Implementation | B13: Services | C13: 79300 | D13: 25200
A14: Nimbus Academy | B14: Training | C14: 94700 | D14: 24600
A15: Vega Core | B15: Subscriptions | C15: 30300 | D15: 12100
A16: Vega Pro | B16: Subscriptions | C16: 39000 | D16: 10100
... A49: Zephyr Academy (launch FY27) | B49: Training | C49: 107000 | D49: 52800
A50: Total | C50: =SUM(C5:C44) -> 2588500 | D50: =SUM(D5:D49) -> 1227300

Sheet May
A1: May 2027 - product revenue plan
A2: Units: USD
A4: Product line | B4: Category | C4: Revenue | D4: COGS
A5: Atlas Core | B5: Subscriptions | C5: 114300 | D5: 45500
A6: Atlas Pro | B6: Subscriptions | C6: 37600 | D6: 17800
A7: Atlas Edge | B7: Hardware | C7: 111900 | D7: 56500
A8: Atlas Implementation | B8: Services | C8: 85700 | D8: 41000
A9: Atlas Academy | B9: Training | C9: 34400 | D9: 11600
A10: Nimbus Core | B10: Subscriptions | C10: 113300 | D10: 46400
A11: Nimbus Pro | B11: Subscriptions | C11: 68100 | D11: 33500
A12: Nimbus Edge | B12: Hardware | C12: 68000 | D12: 33700
A13: Nimbus Implementation | B13: Services | C13: 85200 | D13: 27100
A14: Nimbus Academy | B14: Training | C14: 100300 | D14: 26000
A15: Vega Core | B15: Subscriptions | C15: 30000 | D15: 12000
A16: Vega Pro | B16: Subscriptions | C16: 38700 | D16: 10100
... A49: Zephyr Academy (launch FY27) | B49: Training | C49: 99600 | D49: 49100
A50: Total | C50: =SUM(C5:C44) -> 2611700 | D50: =SUM(D5:D49) -> 1236700

Sheet Jun
A1: Jun 2027 - product revenue plan
A2: Units: USD
A4: Product line | B4: Category | C4: Revenue | D4: COGS
A5: Atlas Core | B5: Subscriptions | C5: 110200 | D5: 43900
A6: Atlas Pro | B6: Subscriptions | C6: 43200 | D6: 20400
A7: Atlas Edge | B7: Hardware | C7: 114100 | D7: 57600
A8: Atlas Implementation | B8: Services | C8: 91100 | D8: 43600
A9: Atlas Academy | B9: Training | C9: 34300 | D9: 11500
A10: Nimbus Core | B10: Subscriptions | C10: 118900 | D10: 48700
A11: Nimbus Pro | B11: Subscriptions | C11: 67400 | D11: 33200
A12: Nimbus Edge | B12: Hardware | C12: 75600 | D12: 37500
A13: Nimbus Implementation | B13: Services | C13: 92300 | D13: 29300
A14: Nimbus Academy | B14: Training | C14: 108600 | D14: 28200
A15: Vega Core | B15: Subscriptions | C15: 31900 | D15: 12700
A16: Vega Pro | B16: Subscriptions | C16: 41000 | D16: 10700
... A49: Zephyr Academy (launch FY27) | B49: Training | C49: 114900 | D49: 56700
A50: Total | C50: =SUM(C5:C44) -> 2762200 | D50: =SUM(D5:D49) -> 1316600

Sheet Jul
A1: Jul 2027 - product revenue plan
A2: Units: USD
A4: Product line | B4: Category | C4: Revenue | D4: COGS
A5: Atlas Core | B5: Subscriptions | C5: 99800 | D5: 39700
A6: Atlas Pro | B6: Subscriptions | C6: 38300 | D6: 18100
A7: Atlas Edge | B7: Hardware | C7: 98600 | D7: 49800
A8: Atlas Implementation | B8: Services | C8: 80800 | D8: 38600
A9: Atlas Academy | B9: Training | C9: 35100 | D9: 11800
A10: Nimbus Core | B10: Subscriptions | C10: 99200 | D10: 40600
A11: Nimbus Pro | B11: Subscriptions | C11: 70000 | D11: 34500
A12: Nimbus Edge | B12: Hardware | C12: 68200 | D12: 33800
A13: Nimbus Implementation | B13: Services | C13: 78200 | D13: 24800
A14: Nimbus Academy | B14: Training | C14: 92400 | D14: 24000
A15: Vega Core | B15: Subscriptions | C15: 27100 | D15: 10800
A16: Vega Pro | B16: Subscriptions | C16: 38200 | D16: 9900
... A49: Zephyr Academy (launch FY27) | B49: Training | C49: 95600 | D49: 47100
A50: Total | C50: =SUM(C5:C44) -> 2516100 | D50: =SUM(D5:D49) -> 1189600

Sheet Aug
A1: Aug 2027 - product revenue plan
A2: Units: USD '000
A4: Product line | B4: Category | C4: Revenue | D4: COGS
A5: Atlas Core | B5: Subscriptions | C5: 105.6 | D5: 42
A6: Atlas Pro | B6: Subscriptions | C6: 35.1 | D6: 16.6
A7: Atlas Edge | B7: Hardware | C7: 102.3 | D7: 51.6
A8: Atlas Implementation | B8: Services | C8: 76.1 | D8: 36.4
A9: Atlas Academy | B9: Training | C9: 32.9 | D9: 11.1
A10: Nimbus Core | B10: Subscriptions | C10: 101.5 | D10: 41.5
A11: Nimbus Pro | B11: Subscriptions | C11: 65.3 | D11: 32.2
A12: Nimbus Edge | B12: Hardware | C12: 59.6 | D12: 29.6
A13: Nimbus Implementation | B13: Services | C13: 74.5 | D13: 23.7
A14: Nimbus Academy | B14: Training | C14: 90.5 | D14: 23.5
A15: Vega Core | B15: Subscriptions | C15: 26.9 | D15: 10.7
A16: Vega Pro | B16: Subscriptions | C16: 38.8 | D16: 10.1
... A49: Zephyr Academy (launch FY27) | B49: Training | C49: 97.1 | D49: 47.9
A50: Total | C50: =SUM(C5:C44) -> 2483.8 | D50: =SUM(D5:D49) -> 1180.1

Sheet Sep
A1: Sep 2027 - product revenue plan
A2: Units: USD
A4: Product line | B4: Category | C4: Revenue | D4: COGS
A5: Atlas Core | B5: Subscriptions | C5: 118000 | D5: 47000
A6: Atlas Pro | B6: Subscriptions | C6: 42900 | D6: 20300
A7: Atlas Edge | B7: Hardware | C7: 111200 | D7: 56100
A8: Atlas Implementation | B8: Services | C8: 83600 | D8: 40000
A9: Atlas Academy | B9: Training | C9: 36600 | D9: 12300
A10: Nimbus Core | B10: Subscriptions | C10: 109700 | D10: 44900
A11: Nimbus Pro | B11: Subscriptions | C11: 75700 | D11: 37300
A12: Nimbus Edge | B12: Hardware | C12: 70400 | D12: 34900
A13: Nimbus Implementation | B13: Services | C13: 90800 | D13: 28800
A14: Nimbus Academy | B14: Training | C14: 113200 | D14: 29400
A15: Vega Core | B15: Subscriptions | C15: 31600 | D15: 12600
A16: Vega Pro | B16: Subscriptions | C16: 44700 | D16: 11600
... A49: Zephyr Academy (launch FY27) | B49: Training | C49: 105600 | D49: 52100
A50: Total | C50: =SUM(C5:C44) -> 2847300 | D50: =SUM(D5:D49) -> 1344900

Sheet Oct
A1: Oct 2027 - product revenue plan
A2: Units: USD
A4: Product line | B4: Category | C4: Revenue | D4: COGS
A5: Atlas Core | B5: Subscriptions | C5: 109700 | D5: 43700
A6: Atlas Pro | B6: Subscriptions | C6: 41000 | D6: 19400
A7: Atlas Edge | B7: Hardware | C7: 103900 | D7: 52500
A8: Atlas Implementation | B8: Services | C8: 82400 | D8: 39400
A9: Atlas Academy | B9: Training | C9: 33900 | D9: 11400
A10: Nimbus Core | B10: Subscriptions | C10: 104700 | D10: 42800
A11: Nimbus Pro | B11: Subscriptions | C11: 68200 | D11: 33600
A12: Nimbus Edge | B12: Hardware | C12: 72400 | D12: 35900
A13: Nimbus Implementation | B13: Services | C13: 84300 | D13: 26800
A14: Nimbus Academy | B14: Training | C14: 108100 | D14: 28000
A15: Vega Core | B15: Subscriptions | C15: 29700 | D15: 11900
A16: Vega Pro | B16: Subscriptions | C16: 41500 | D16: 10800
... A49: Zephyr Academy (launch FY27) | B49: Training | C49: 112200 | D49: 55300
A50: Total | C50: =SUM(C5:C44) -> 2690000 | D50: =SUM(D5:D49) -> 1283000

Sheet Nov
A1: Nov 2027 - product revenue plan
A2: Units: USD
A4: Product line | B4: Category | C4: Revenue | D4: COGS
A5: Atlas Core | B5: Subscriptions | C5: 120700 | D5: 48100
A6: Atlas Pro | B6: Subscriptions | C6: 40100 | D6: 19000
A7: Atlas Edge | B7: Hardware | C7: 104500 | D7: 52800
A8: Atlas Implementation | B8: Services | C8: 83000 | D8: 39700
A9: Atlas Academy | B9: Training | C9: 35700 | D9: 12000
A10: Nimbus Core | B10: Subscriptions | C10: 108200 | D10: 44300
A11: Nimbus Pro | B11: Subscriptions | C11: 68900 | D11: 33900
A12: Nimbus Edge | B12: Hardware | C12: 74800 | D12: 37100
A13: Nimbus Implementation | B13: Services | C13: 91000 | D13: 28900
A14: Nimbus Academy | B14: Training | C14: 102900 | D14: 26700
A15: Vega Core | B15: Subscriptions | C15: 29400 | D15: 11700
A16: Vega Pro | B16: Subscriptions | C16: 47000 | D16: 12200
... A49: Zephyr Academy (launch FY27) | B49: Training | C49: 115200 | D49: 56800
A50: Total | C50: =SUM(C5:C44) -> 2772500 | D50: =SUM(D5:D49) -> 1322800

Sheet Dec
A1: Dec 2027 - product revenue plan
A2: Units: USD
A4: Product line | B4: Category | C4: Revenue | D4: COGS
A5: Atlas Core | B5: Subscriptions | C5: 137400 | D5: 54700
A6: Atlas Pro | B6: Subscriptions | C6: 47300 | D6: 22400
A7: Atlas Edge | B7: Hardware | C7: 126100 | D7: 63700
A8: Atlas Implementation | B8: Services | C8: 95100 | D8: 45500
A9: Atlas Academy | B9: Training | C9: 43900 | D9: 14800
A10: Nimbus Core | B10: Subscriptions | C10: 123700 | D10: 50600
A11: Nimbus Pro | B11: Subscriptions | C11: 82200 | D11: 40500
A12: Nimbus Edge | B12: Hardware | C12: 82700 | D12: 41000
A13: Nimbus Implementation | B13: Services | C13: 97300 | D13: 30900
A14: Nimbus Academy | B14: Training | C14: 120900 | D14: 31300
A15: Vega Core | B15: Subscriptions | C15: 33900 | D15: 13500
A16: Vega Pro | B16: Subscriptions | C16: 46200 | D16: 12000
... A49: Zephyr Academy (launch FY27) | B49: Training | C49: 131800 | D49: 65000
A50: Total | C50: =SUM(C5:C44) -> 3124900 | D50: =SUM(D5:D49) -> 1489500
