Workbook

Sheet Approvals
A1: Quote Q-26-0412 - Discount Approval
A2: Customer: Meridian Health Systems | Prepared by Deal Desk | Yellow = editable
A4: Line | B4: SKU | C4: Description | D4: Region | E4: Qty | F4: Requested Disc | G4: List Price (USD) | H4: Volume Disc | I4: Promo | J4: Total Disc | K4: Net Unit Price | L4: Net Line (USD) | M4: Active | N4: Unit Cost | O4: Margin % | P4: Approval Tier | Q4: Net Line (INR lakh)
A5: 1 | B5: PRO-100 | C5: =IFERROR(VLOOKUP(B5,SKUs!$A$2:$B$21,2,FALSE),"") -> Pro License - 1 seat | D5: NA | E5: 40 | F5: 0.1 | G5: =IFERROR(VLOOKUP(B5,ListPrice_USD!$A$2:$B$23,2,FALSE),0) -> 899 | H5: =INDEX(Discounts!$B$5:$B$10,MATCH(E5,Discounts!$A$5:$A$10,1)) -> 0.05 | I5: =IF(TODAY()<=Discounts!$B$13,Discounts!$B$12,0) -> 0.05 | J5: =F5+H5+I5 -> 0.2 | K5: =G5*(1-J5) -> 719.2 | L5: =ROUND(K5*E5,2) -> 28768 | M5: =IFERROR(VLOOKUP(B5,SKUs!$A$2:$E$21,5,FALSE),"") -> Y | N5: =IFERROR(VLOOKUP(B5,SKUs!$A$2:$D$21,4,FALSE),0) -> 197.78 | O5: =IFERROR((K5-N5)/K5,0) -> 0.725 | P5: =IF(AND(OR(J5>=0.3,L5>100000),J5>=0.2,L5>25000),"VP",IF(J5>=0.15,"Director","Manager")) -> Director | Q5: =IF(D5="India",E5*IFERROR(VLOOKUP(B5,ListPrice_INR_lakh!$A$4:$B$25,2,FALSE),0)*(1-J5),"")
A6: 2 | B6: PRO-140 | C6: =IFERROR(VLOOKUP(B6,SKUs!$A$2:$B$21,2,FALSE),"") -> Pro License - Team (5) | D6: EMEA | E6: 12 | F6: 0.08 | G6: =IFERROR(VLOOKUP(B6,ListPrice_USD!$A$2:$B$23,2,FALSE),0) -> 1150 | H6: =INDEX(Discounts!$B$5:$B$10,MATCH(E6,Discounts!$A$5:$A$10,1)) -> 0.05 | I6: =IF(TODAY()<=Discounts!$B$13,Discounts!$B$12,0) -> 0.05 | J6: =F6+H6+I6 -> 0.18 | K6: =G6*(1-J6) -> 943 | L6: =ROUND(K6*E6,2) -> 11316 | M6: =IFERROR(VLOOKUP(B6,SKUs!$A$2:$E$21,5,FALSE),"") -> Y | N6: =IFERROR(VLOOKUP(B6,SKUs!$A$2:$D$21,4,FALSE),0) -> 310.8 | O6: =IFERROR((K6-N6)/K6,0) -> 0.67041357 | P6: =IF(AND(OR(J6>=0.3,L6>100000),J6>=0.2,L6>25000),"VP",IF(J6>=0.15,"Director","Manager")) -> Director | Q6: =IF(D6="India",E6*IFERROR(VLOOKUP(B6,ListPrice_INR_lakh!$A$4:$B$25,2,FALSE),0)*(1-J6),"")
A7: 3 | B7: ENT-200 | C7: =IFERROR(VLOOKUP(B7,SKUs!$A$2:$B$21,2,FALSE),"") -> Enterprise License - 1 seat | D7: NA | E7: 120 | F7: 0.15 | G7: =IFERROR(VLOOKUP(B7,ListPrice_USD!$A$2:$B$23,2,FALSE),0) -> 1849 | H7: =INDEX(Discounts!$B$5:$B$10,MATCH(E7,Discounts!$A$5:$A$10,1)) -> 0.125 | I7: =IF(TODAY()<=Discounts!$B$13,Discounts!$B$12,0) -> 0.05 | J7: =F7+H7+I7 -> 0.325 | K7: =G7*(1-J7) -> 1248.075 | L7: =ROUND(K7*E7,2) -> 149769 | M7: =IFERROR(VLOOKUP(B7,SKUs!$A$2:$E$21,5,FALSE),"") -> Y | N7: =IFERROR(VLOOKUP(B7,SKUs!$A$2:$D$21,4,FALSE),0) -> 369.8 | O7: =IFERROR((K7-N7)/K7,0) -> 0.7037037 | P7: =IF(AND(OR(J7>=0.3,L7>100000),J7>=0.2,L7>25000),"VP",IF(J7>=0.15,"Director","Manager")) -> VP | Q7: =IF(D7="India",E7*IFERROR(VLOOKUP(B7,ListPrice_INR_lakh!$A$4:$B$25,2,FALSE),0)*(1-J7),"")
A8: 4 | B8: ENT-220 | C8: =IFERROR(VLOOKUP(B8,SKUs!$A$2:$B$21,2,FALSE),"") -> Enterprise License - Site | D8: APAC | E8: 1 | F8: 0.12 | G8: =IFERROR(VLOOKUP(B8,ListPrice_USD!$A$2:$B$23,2,FALSE),0) -> 4800 | H8: =INDEX(Discounts!$B$5:$B$10,MATCH(E8,Discounts!$A$5:$A$10,1)) -> 0 | I8: =IF(TODAY()<=Discounts!$B$13,Discounts!$B$12,0) -> 0.05 | J8: =F8+H8+I8 -> 0.17 | K8: =G8*(1-J8) -> 3984 | L8: =ROUND(K8*E8,2) -> 3984 | M8: =IFERROR(VLOOKUP(B8,SKUs!$A$2:$E$21,5,FALSE),"") -> Y | N8: =IFERROR(VLOOKUP(B8,SKUs!$A$2:$D$21,4,FALSE),0) -> 1102.5 | O8: =IFERROR((K8-N8)/K8,0) -> 0.72326807 | P8: =IF(AND(OR(J8>=0.3,L8>100000),J8>=0.2,L8>25000),"VP",IF(J8>=0.15,"Director","Manager")) -> Director | Q8: =IF(D8="India",E8*IFERROR(VLOOKUP(B8,ListPrice_INR_lakh!$A$4:$B$25,2,FALSE),0)*(1-J8),"")
A9: 5 | B9: ANL-300 | C9: =IFERROR(VLOOKUP(B9,SKUs!$A$2:$B$21,2,FALSE),"") -> Analytics Module | D9: India | E9: 30 | F9: 0.1 | G9: =IFERROR(VLOOKUP(B9,ListPrice_USD!$A$2:$B$23,2,FALSE),0) -> 649.5 | H9: =INDEX(Discounts!$B$5:$B$10,MATCH(E9,Discounts!$A$5:$A$10,1)) -> 0.05 | I9: =IF(TODAY()<=Discounts!$B$13,Discounts!$B$12,0) -> 0.05 | J9: =F9+H9+I9 -> 0.2 | K9: =G9*(1-J9) -> 519.6 | L9: =ROUND(K9*E9,2) -> 15588 | M9: =IFERROR(VLOOKUP(B9,SKUs!$A$2:$E$21,5,FALSE),"") -> Y | N9: =IFERROR(VLOOKUP(B9,SKUs!$A$2:$D$21,4,FALSE),0) -> 162.38 | O9: =IFERROR((K9-N9)/K9,0) -> 0.68749038 | P9: =IF(AND(OR(J9>=0.3,L9>100000),J9>=0.2,L9>25000),"VP",IF(J9>=0.15,"Director","Manager")) -> Director | Q9: =IF(D9="India",E9*IFERROR(VLOOKUP(B9,ListPrice_INR_lakh!$A$4:$B$25,2,FALSE),0)*(1-J9),"") -> 12.969216
A10: 6 | B10: SEC-310 | C10: =IFERROR(VLOOKUP(B10,SKUs!$A$2:$B$21,2,FALSE),"") -> Security Add-on | D10: India | E10: 60 | F10: 0.05 | G10: =IFERROR(VLOOKUP(B10,ListPrice_USD!$A$2:$B$23,2,FALSE),0) -> 412.75 | H10: =INDEX(Discounts!$B$5:$B$10,MATCH(E10,Discounts!$A$5:$A$10,1)) -> 0.075 | I10: =IF(TODAY()<=Discounts!$B$13,Discounts!$B$12,0) -> 0.05 | J10: =F10+H10+I10 -> 0.175 | K10: =G10*(1-J10) -> 340.51875 | L10: =ROUND(K10*E10,2) -> 20431.13 | M10: =IFERROR(VLOOKUP(B10,SKUs!$A$2:$E$21,5,FALSE),"") -> Y | N10: =IFERROR(VLOOKUP(B10,SKUs!$A$2:$D$21,4,FALSE),0) -> 111.44 | O10: =IFERROR((K10-N10)/K10,0) -> 0.67273461 | P10: =IF(AND(OR(J10>=0.3,L10>100000),J10>=0.2,L10>25000),"VP",IF(J10>=0.15,"Director","Manager")) -> Director | Q10: =IF(D10="India",E10*IFERROR(VLOOKUP(B10,ListPrice_INR_lakh!$A$4:$B$25,2,FALSE),0)*(1-J10),"") -> 16.998696
A11: 7 | B11: HW-500 | C11: =IFERROR(VLOOKUP(B11,SKUs!$A$2:$B$21,2,FALSE),"") -> Edge Gateway G2 | D11: NA | E11: 300 | F11: 0.12 | G11: =IFERROR(VLOOKUP(B11,ListPrice_USD!$A$2:$B$23,2,FALSE),0) -> 1249.99 | H11: =INDEX(Discounts!$B$5:$B$10,MATCH(E11,Discounts!$A$5:$A$10,1)) -> 0.15 | I11: =IF(TODAY()<=Discounts!$B$13,Discounts!$B$12,0) -> 0.05 | J11: =F11+H11+I11 -> 0.32 | K11: =G11*(1-J11) -> 849.9932 | L11: =ROUND(K11*E11,2) -> 254997.96 | M11: =IFERROR(VLOOKUP(B11,SKUs!$A$2:$E$21,5,FALSE),"") -> Y | N11: =IFERROR(VLOOKUP(B11,SKUs!$A$2:$D$21,4,FALSE),0) -> 1037.49 | O11: =IFERROR((K11-N11)/K11,0) -> -0.22058624 | P11: =IF(AND(OR(J11>=0.3,L11>100000),J11>=0.2,L11>25000),"VP",IF(J11>=0.15,"Director","Manager")) -> VP | Q11: =IF(D11="India",E11*IFERROR(VLOOKUP(B11,ListPrice_INR_lakh!$A$4:$B$25,2,FALSE),0)*(1-J11),"")
A12: 8 | B12: HW-510 | C12: =IFERROR(VLOOKUP(B12,SKUs!$A$2:$B$21,2,FALSE),"") -> Edge Gateway G3 | D12: EMEA | E12: 18 | F12: 0.2 | G12: =IFERROR(VLOOKUP(B12,ListPrice_USD!$A$2:$B$23,2,FALSE),0) -> 1699.99 | H12: =INDEX(Discounts!$B$5:$B$10,MATCH(E12,Discounts!$A$5:$A$10,1)) -> 0.05 | I12: =IF(TODAY()<=Discounts!$B$13,Discounts!$B$12,0) -> 0.05 | J12: =F12+H12+I12 -> 0.3 | K12: =G12*(1-J12) -> 1189.993 | L12: =ROUND(K12*E12,2) -> 21419.87 | M12: =IFERROR(VLOOKUP(B12,SKUs!$A$2:$E$21,5,FALSE),"") -> Y | N12: =IFERROR(VLOOKUP(B12,SKUs!$A$2:$D$21,4,FALSE),0) -> 1359.99 | O12: =IFERROR((K12-N12)/K12,0) -> -0.14285546 | P12: =IF(AND(OR(J12>=0.3,L12>100000),J12>=0.2,L12>25000),"VP",IF(J12>=0.15,"Director","Manager")) -> Director | Q12: =IF(D12="India",E12*IFERROR(VLOOKUP(B12,ListPrice_INR_lakh!$A$4:$B$25,2,FALSE),0)*(1-J12),"")
A13: 9 | B13: HW-520 | C13: =IFERROR(VLOOKUP(B13,SKUs!$A$2:$B$21,2,FALSE),"") -> Sensor Pack (10) | D13: APAC | E13: 75 | F13: 0.05 | G13: =IFERROR(VLOOKUP(B13,ListPrice_USD!$A$2:$B$23,2,FALSE),0) -> 389.95 | H13: =INDEX(Discounts!$B$5:$B$10,MATCH(E13,Discounts!$A$5:$A$10,1)) -> 0.075 | I13: =IF(TODAY()<=Discounts!$B$13,Discounts!$B$12,0) -> 0.05 | J13: =F13+H13+I13 -> 0.175 | K13: =G13*(1-J13) -> 321.70875 | L13: =ROUND(K13*E13,2) -> 24128.16 | M13: =IFERROR(VLOOKUP(B13,SKUs!$A$2:$E$21,5,FALSE),"") -> Y | N13: =IFERROR(VLOOKUP(B13,SKUs!$A$2:$D$21,4,FALSE),0) -> 335.36 | O13: =IFERROR((K13-N13)/K13,0) -> -0.042433568 | P13: =IF(AND(OR(J13>=0.3,L13>100000),J13>=0.2,L13>25000),"VP",IF(J13>=0.15,"Director","Manager")) -> Director | Q13: =IF(D13="India",E13*IFERROR(VLOOKUP(B13,ListPrice_INR_lakh!$A$4:$B$25,2,FALSE),0)*(1-J13),"")
A14: 10 | B14: HW-530 | C14: =IFERROR(VLOOKUP(B14,SKUs!$A$2:$B$21,2,FALSE),"") -> Rack Mount Kit | D14: India | E14: 8 | F14: 0 | G14: =IFERROR(VLOOKUP(B14,ListPrice_USD!$A$2:$B$23,2,FALSE),0) -> 145.6 | H14: =INDEX(Discounts!$B$5:$B$10,MATCH(E14,Discounts!$A$5:$A$10,1)) -> 0 | I14: =IF(TODAY()<=Discounts!$B$13,Discounts!$B$12,0) -> 0.05 | J14: =F14+H14+I14 -> 0.05 | K14: =G14*(1-J14) -> 138.32 | L14: =ROUND(K14*E14,2) -> 1106.56 | M14: =IFERROR(VLOOKUP(B14,SKUs!$A$2:$E$21,5,FALSE),"") -> Y | N14: =IFERROR(VLOOKUP(B14,SKUs!$A$2:$D$21,4,FALSE),0) -> 113.57 | O14: =IFERROR((K14-N14)/K14,0) -> 0.17893291 | P14: =IF(AND(OR(J14>=0.3,L14>100000),J14>=0.2,L14>25000),"VP",IF(J14>=0.15,"Director","Manager")) -> Manager | Q14: =IF(D14="India",E14*IFERROR(VLOOKUP(B14,ListPrice_INR_lakh!$A$4:$B$25,2,FALSE),0)*(1-J14),"") -> 0.92065792
A15: 11 | B15: SRV-010 | C15: =IFERROR(VLOOKUP(B15,SKUs!$A$2:$B$21,2,FALSE),"") -> Implementation - Standard | D15: NA | E15: 2 | F15: 0.1 | G15: =IFERROR(VLOOKUP(B15,ListPrice_USD!$A$2:$B$23,2,FALSE),0) -> 7500 | H15: =INDEX(Discounts!$B$5:$B$10,MATCH(E15,Discounts!$A$5:$A$10,1)) -> 0 | I15: =IF(TODAY()<=Discounts!$B$13,Discounts!$B$12,0) -> 0.05 | J15: =F15+H15+I15 -> 0.15 | K15: =G15*(1-J15) -> 6375 | L15: =ROUND(K15*E15,2) -> 12750 | M15: =IFERROR(VLOOKUP(B15,SKUs!$A$2:$E$21,5,FALSE),"") -> Y | N15: =IFERROR(VLOOKUP(B15,SKUs!$A$2:$D$21,4,FALSE),0) -> 4650 | O15: =IFERROR((K15-N15)/K15,0) -> 0.27058824 | P15: =IF(AND(OR(J15>=0.3,L15>100000),J15>=0.2,L15>25000),"VP",IF(J15>=0.15,"Director","Manager")) -> Director | Q15: =IF(D15="India",E15*IFERROR(VLOOKUP(B15,ListPrice_INR_lakh!$A$4:$B$25,2,FALSE),0)*(1-J15),"")
A16: 12 | B16: SRV-020 | C16: =IFERROR(VLOOKUP(B16,SKUs!$A$2:$B$21,2,FALSE),"") -> Implementation - Premium | D16: EMEA | E16: 1 | F16: 0.18 | G16: =IFERROR(VLOOKUP(B16,ListPrice_USD!$A$2:$B$23,2,FALSE),0) -> 14200 | H16: =INDEX(Discounts!$B$5:$B$10,MATCH(E16,Discounts!$A$5:$A$10,1)) -> 0 | I16: =IF(TODAY()<=Discounts!$B$13,Discounts!$B$12,0) -> 0.05 | J16: =F16+H16+I16 -> 0.23 | K16: =G16*(1-J16) -> 10934 | L16: =ROUND(K16*E16,2) -> 10934 | M16: =IFERROR(VLOOKUP(B16,SKUs!$A$2:$E$21,5,FALSE),"") -> Y | N16: =IFERROR(VLOOKUP(B16,SKUs!$A$2:$D$21,4,FALSE),0) -> 8236 | O16: =IFERROR((K16-N16)/K16,0) -> 0.24675325 | P16: =IF(AND(OR(J16>=0.3,L16>100000),J16>=0.2,L16>25000),"VP",IF(J16>=0.15,"Director","Manager")) -> Director | Q16: =IF(D16="India",E16*IFERROR(VLOOKUP(B16,ListPrice_INR_lakh!$A$4:$B$25,2,FALSE),0)*(1-J16),"")
... A28: 24 | B28: PRO-100 | C28: =IFERROR(VLOOKUP(B28,SKUs!$A$2:$B$21,2,FALSE),"") -> Pro License - 1 seat | D28: APAC | E28: 9 | F28: 0 | G28: =IFERROR(VLOOKUP(B28,ListPrice_USD!$A$2:$B$23,2,FALSE),0) -> 899 | H28: =INDEX(Discounts!$B$5:$B$10,MATCH(E28,Discounts!$A$5:$A$10,1)) -> 0 | I28: =IF(TODAY()<=Discounts!$B$13,Discounts!$B$12,0) -> 0.05 | J28: =F28+H28+I28 -> 0.05 | K28: =G28*(1-J28) -> 854.05 | L28: =ROUND(K28*E28,2) -> 7686.45 | M28: =IFERROR(VLOOKUP(B28,SKUs!$A$2:$E$21,5,FALSE),"") -> Y | N28: =IFERROR(VLOOKUP(B28,SKUs!$A$2:$D$21,4,FALSE),0) -> 197.78 | O28: =IFERROR((K28-N28)/K28,0) -> 0.76842105 | P28: =IF(AND(OR(J28>=0.3,L28>100000),J28>=0.2,L28>25000),"VP",IF(J28>=0.15,"Director","Manager")) -> Manager | Q28: =IF(D28="India",E28*IFERROR(VLOOKUP(B28,ListPrice_INR_lakh!$A$4:$B$25,2,FALSE),0)*(1-J28),"")
J30: Quote total (USD) | L30: =SUM(L5:L28) -> 1034251.5
J31: Quote total at unit price x qty | L31: =SUMPRODUCT(K5:K28,E5:E28) -> 1034251.5
J32: Revenue from active SKUs | L32: =SUMPRODUCT(--(M5:M28="Y"),L5:L28) -> 992993.52
J33: Blended margin | L33: =IFERROR((L30-SUMPRODUCT(N5:N28,E5:E28))/L30,0) -> 0.33831071
J34: Highest approval required | L34: =IF(COUNTIF(P5:P28,"VP")>0,"VP",IF(COUNTIF(P5:P28,"Director")>0,"Director","Manager")) -> VP

Sheet SKUs
A1: SKU | B1: Description | C1: Category | D1: Unit Cost (USD) | E1: Active
A2: PRO-100 | B2: Pro License - 1 seat | C2: Software | D2: 197.78 | E2: Y
A3: PRO-140 | B3: Pro License - Team (5) | C3: Software | D3: 310.8 | E3: Y
A4: ENT-200 | B4: Enterprise License - 1 seat | C4: Software | D4: 369.8 | E4: Y
A5: ENT-220 | B5: Enterprise License - Site | C5: Software | D5: 1102.5 | E5: Y
A6: ANL-300 | B6: Analytics Module | C6: Software | D6: 162.38 | E6: Y
A7: SEC-310 | B7: Security Add-on | C7: Software | D7: 111.44 | E7: Y
A8: HW-500 | B8: Edge Gateway G2 | C8: Hardware | D8: 1037.49 | E8: Y
A9: HW-510 | B9: Edge Gateway G3 | C9: Hardware | D9: 1359.99 | E9: Y
A10: HW-520 | B10: Sensor Pack (10) | C10: Hardware | D10: 335.36 | E10: Y
A11: HW-530 | B11: Rack Mount Kit | C11: Hardware | D11: 113.57 | E11: Y
A12: SRV-010 | B12: Implementation - Standard | C12: Services | D12: 4650 | E12: Y
A13: SRV-020 | B13: Implementation - Premium | C13: Services | D13: 8236 | E13: Y
... A19: SUP-110 | B19: Standard Support (annual) | C19: Support | D19: 363.72 | E19: Y
A20: 46082 | B20: Marketing Analytics Lite | C20: Software | D20: 74.75 | E20: Y
A21: 100000 | B21: 1E5 Data Connector | C21: Software | D21: 136.5 | E21: Y

Sheet ListPrice_USD
A1: SKU | B1: List Price (USD) | C1: Effective From
A2: PRO-100 | B2: 899 | C2: 46113
A3: PRO-140 | B3: 1150 | C3: 45748
A4: ENT-200 | B4: 1849 | C4: 46113
A5: ENT-220 | B5: 4800 | C5: 45748
A6: ANL-300 | B6: 649.5 | C6: 46113
A7: SEC-310 | B7: 412.75 | C7: 46113
A8: HW-500 | B8: 1249.99 | C8: 46113
A9: HW-510 | B9: 1699.99 | C9: 46113
A10: HW-520 | B10: 389.95 | C10: 46113
A11: HW-530 | B11: 145.6 | C11: 46113
A12: SRV-010 | B12: 7500 | C12: 46113
A13: SRV-020 | B13: 14200 | C13: 46113
... A19: SUP-110 | B19: 1299 | C19: 46113
A20: 46082 | B20: 299 | C20: 46113
A21: 100000 | B21: 525 | C21: 46113
A22: ENT-220 | B22: 5250 | C22: 46204
A23: PRO-140 | B23: 1295 | C23: 46204

Sheet ListPrice_INR_lakh
A1: List prices in INR lakh (for India quotes)
A3: SKU | B3: List Price (INR lakh)
A4: =ListPrice_USD!A2 -> PRO-100 | B4: =ListPrice_USD!B2*83.2/100000 -> 0.747968
A5: =ListPrice_USD!A3 -> PRO-140 | B5: =ListPrice_USD!B3*83.2/100000 -> 0.9568
A6: =ListPrice_USD!A4 -> ENT-200 | B6: =ListPrice_USD!B4*83.2/100000 -> 1.538368
A7: =ListPrice_USD!A5 -> ENT-220 | B7: =ListPrice_USD!B5*83.2/100000 -> 3.9936
A8: =ListPrice_USD!A6 -> ANL-300 | B8: =ListPrice_USD!B6*83.2/100000 -> 0.540384
A9: =ListPrice_USD!A7 -> SEC-310 | B9: =ListPrice_USD!B7*83.2/100000 -> 0.343408
A10: =ListPrice_USD!A8 -> HW-500 | B10: =ListPrice_USD!B8*83.2/100000 -> 1.0399917
A11: =ListPrice_USD!A9 -> HW-510 | B11: =ListPrice_USD!B9*83.2/100000 -> 1.4143917
A12: =ListPrice_USD!A10 -> HW-520 | B12: =ListPrice_USD!B10*83.2/100000 -> 0.3244384
A13: =ListPrice_USD!A11 -> HW-530 | B13: =ListPrice_USD!B11*83.2/100000 -> 0.1211392
A14: =ListPrice_USD!A12 -> SRV-010 | B14: =ListPrice_USD!B12*83.2/100000 -> 6.24
A15: =ListPrice_USD!A13 -> SRV-020 | B15: =ListPrice_USD!B13*83.2/100000 -> 11.8144
... A25: =ListPrice_USD!A23 -> PRO-140 | B25: =ListPrice_USD!B23*83.2/100000 -> 1.07744

Sheet Discounts
A1: Discount policy
A3: Volume bands
A4: Min Qty | B4: Volume Discount
A5: 1 | B5: 0
A6: 10 | B6: 0.05
A7: 50 | B7: 0.1
A8: 25 | B8: 0.075
A9: 100 | B9: 0.125
A10: 250 | B10: 0.15
A12: Year-end promo discount | B12: 0.05
A13: Promo valid until | B13: 46387
A15: Approval matrix: Manager < 15% total discount; Director 15-30%; VP >= 30%, or >= 20% on lines above USD 100k.
A16: Margin floor: 12%. Lines below the floor cannot be approved.

Sheet lists
A1: Regions | B1: Categories
A2: North | B2: Software
A3: South | B3: Hardware
A4: East | B4: Services
A5: West | B5: Training
B6: Support
